gasparse.cpython-311-i386-linux-gnu.so
gasparse-0.0.6a0.dist-info/top_level.txt
gasparse-0.0.6a0.dist-info/WHEEL
gasparse-0.0.6a0.dist-info/RECORD
gasparse-0.0.6a0.dist-info/METADATA
gasparse-0.0.6a0.dist-info/LICENSE.txt
