Metadata-Version: 2.1
Name: gasparse
Version: 0.0.6a0
Summary: A python library written entirely in C for Geometric Algebras to deal with sparse multivector arrays
Author: Anon 6666
Author-email: completelyanonymous6666@gmail.com
License: MIT
Requires-Python: >=3.7
License-File: LICENSE.txt
